twdown/__init__.py
twdown/_impl.py
twdown-0.0.1.dist-info/LICENSE
twdown-0.0.1.dist-info/METADATA
twdown-0.0.1.dist-info/WHEEL
twdown-0.0.1.dist-info/top_level.txt
twdown-0.0.1.dist-info/RECORD
